qoqo-1.21.0.dist-info/METADATA
qoqo-1.21.0.dist-info/WHEEL
qoqo-1.21.0.dist-info/licenses/LICENSE
qoqo/DEPENDENCIES
qoqo/LICENSE_FOR_BINARY_DISTRIBUTION
qoqo/PYTHON_LICENSE
qoqo/__init__.py
qoqo/devices.pyi
qoqo/measurements.pyi
qoqo/noise_models.pyi
qoqo/operations.pyi
qoqo/qoqo.cp312-win_amd64.pyd
qoqo/qoqo.pyi
qoqo-1.21.0.dist-info/RECORD
