Metadata-Version: 2.4
Name: qoqo
Version: 1.21.0
Requires-Dist: numpy
Requires-Dist: qoqo-calculator-pyo3>=1.5
Requires-Dist: struqture-py
Requires-Dist: sphinx>=2.1 ; extra == 'docs'
Requires-Dist: nbsphinx ; extra == 'docs'
Requires-Dist: pygments ; extra == 'docs'
Requires-Dist: recommonmark ; extra == 'docs'
Requires-Dist: myst-parser ; extra == 'docs'
Requires-Dist: sphinx-rtd-theme ; extra == 'docs'
Requires-Dist: tomli ; extra == 'docs'
Provides-Extra: docs
License-File: LICENSE
Home-Page: https://github.com/HQSquantumsimulations/qoqo
Maintainer-email: HQS Quantum Simulations GmbH <info@quantumsimulations.de>
License: Apache-2.0 AND Apache-2.0 with LLVM-exception AND MIT AND Unicode-DFS-2016 AND
Requires-Python: >=3.9
